essence_extractor/__init__.py
essence_extractor/main.py
essence_extractor/src/__init__.py
essence_extractor/src/blog_generator.py
essence_extractor/src/blog_media_enhancer.py
essence_extractor/src/cost_management.py
essence_extractor/src/data_models/__init__.py
essence_extractor/src/data_models/file_path_model.py
essence_extractor/src/data_models/llm_model.py
essence_extractor/src/data_models/youtube_url_model.py
essence_extractor/src/downloader.py
essence_extractor/src/transcriber.py
essence_extractor/src/utils/__init__.py
essence_extractor/src/utils/custom_exceptions.py
essence_extractor/src/utils/utils.py
essence_extractor-0.1.1.dist-info/LICENSE
essence_extractor-0.1.1.dist-info/METADATA
essence_extractor-0.1.1.dist-info/WHEEL
essence_extractor-0.1.1.dist-info/entry_points.txt
essence_extractor-0.1.1.dist-info/RECORD
