Metadata-Version: 2.1
Name: essence-extractor
Version: 0.1.1
Summary: Unleash the power of content transformation with EssenceExtractor, a dynamic tool that turbocharges your workflow, turning YouTube videos into engaging, readable blog posts in a snap!
Author: Jurik-001
Requires-Python: >=3.10,<4.0
Classifier: Programming Language :: Python :: 3
Classifier: Programming Language :: Python :: 3.10
Classifier: Programming Language :: Python :: 3.11
Requires-Dist: faiss-cpu (>=1.7.4,<2.0.0)
Requires-Dist: moviepy (>=1.0.3,<2.0.0)
Requires-Dist: openai (>=1.2.4,<2.0.0)
Requires-Dist: openai-whisper (>=20231117,<20231118)
Requires-Dist: pydantic (>=2.5.2,<3.0.0)
Requires-Dist: pytesseract (>=0.3.10,<0.4.0)
Requires-Dist: pytube (>=15.0.0,<16.0.0)
Requires-Dist: sentence-transformers (>=2.2.2,<3.0.0)
Requires-Dist: speechrecognition (>=3.10.0,<4.0.0)
Requires-Dist: tiktoken (>=0.3.3,<0.4.0)
Requires-Dist: tqdm (>=4.66.1,<5.0.0)
